{
  "year": 2021,
  "day": 1,
  "results": {
    "1": [
      {
        "userId": 32289,
        "user": "betaveros (AoC++)",
        "link": "https://github.com/betaveros",
        "place": 1,
        "time": 28
      },
      {
        "userId": 379289,
        "user": "Erik Amirell Eklöf",
        "link": "https://github.com/Eae02",
        "place": 2,
        "time": 29
      },
      {
        "userId": 996955,
        "user": "David Robinson",
        "link": "https://twitter.com/drob",
        "place": 3,
        "time": 31
      },
      {
        "userId": 705153,
        "user": "5space",
        "link": "https://github.com/5space",
        "place": 4,
        "time": 33
      },
      {
        "userId": 26414,
        "user": "mserrano",
        "link": null,
        "place": 5,
        "time": 34
      },
      {
        "userId": 1074314,
        "user": "Alex Oro (AoC++)",
        "link": "/2021/support",
        "place": 6,
        "time": 34
      },
      {
        "userId": 633174,
        "user": "anna (AoC++)",
        "link": "https://github.com/anna328p",
        "place": 7,
        "time": 35
      },
      {
        "userId": 994323,
        "user": "Carl Schildkraut",
        "link": null,
        "place": 8,
        "time": 37
      },
      {
        "userId": 417403,
        "user": "bjebert",
        "link": "https://github.com/bjebert",
        "place": 9,
        "time": 37
      },
      {
        "userId": 201408,
        "user": "Tim Vermeulen (AoC++)",
        "link": "https://github.com/timvermeulen",
        "place": 10,
        "time": 37
      },
      {
        "userId": 52063,
        "user": "Tanner Hoke",
        "link": null,
        "place": 11,
        "time": 37
      },
      {
        "userId": 67806,
        "user": "jonathanpaulson (AoC++)",
        "link": "https://github.com/jonathanpaulson",
        "place": 12,
        "time": 38
      },
      {
        "userId": 102628,
        "user": "kejadlen (AoC++)",
        "link": "https://github.com/kejadlen",
        "place": 13,
        "time": 40
      },
      {
        "userId": 677741,
        "user": "(anonymous user #677741) (AoC++)",
        "link": "/2021/support",
        "place": 14,
        "time": 40
      },
      {
        "userId": 645988,
        "user": "qpwoeirut",
        "link": "https://github.com/qpwoeirut",
        "place": 15,
        "time": 40
      },
      {
        "userId": 1124805,
        "user": "T6",
        "link": "https://github.com/tjjfvi",
        "place": 16,
        "time": 41
      },
      {
        "userId": 181716,
        "user": "evanphoward (AoC++)",
        "link": "https://github.com/evanphoward",
        "place": 17,
        "time": 43
      },
      {
        "userId": 223257,
        "user": "mcpower",
        "link": "https://github.com/mcpower",
        "place": 18,
        "time": 43
      },
      {
        "userId": 1129437,
        "user": "Matthew Yang",
        "link": null,
        "place": 19,
        "time": 43
      },
      {
        "userId": 1567152,
        "user": "Ritwin Narra",
        "link": null,
        "place": 20,
        "time": 44
      },
      {
        "userId": 1568745,
        "user": "Daniel Strizhevsky",
        "link": "https://github.com/danielstrizhevsky",
        "place": 21,
        "time": 44
      },
      {
        "userId": 642453,
        "user": "Jimmy Mårdell (AoC++) (Sponsor)",
        "link": "/2021/support",
        "place": 22,
        "time": 44
      },
      {
        "userId": 3552,
        "user": "Kristian Bjerre Schmidt (AoC++)",
        "link": "/2021/support",
        "place": 23,
        "time": 44
      },
      {
        "userId": 1510407,
        "user": "(anonymous user #1510407) (AoC++)",
        "link": "/2021/support",
        "place": 24,
        "time": 44
      },
      {
        "userId": 514396,
        "user": "connorjayr (AoC++)",
        "link": "https://github.com/connorjayr",
        "place": 25,
        "time": 44
      },
      {
        "userId": 60233,
        "user": "(anonymous user #60233) (AoC++)",
        "link": "/2021/support",
        "place": 26,
        "time": 44
      },
      {
        "userId": 351052,
        "user": "Md Abedin",
        "link": "https://github.com/MdAbedin",
        "place": 27,
        "time": 44
      },
      {
        "userId": 484659,
        "user": "Craig Gidney (AoC++)",
        "link": "https://github.com/Strilanc",
        "place": 28,
        "time": 45
      },
      {
        "userId": 415650,
        "user": "tckmn",
        "link": "https://github.com/tckmn",
        "place": 29,
        "time": 45
      },
      {
        "userId": 684990,
        "user": "D. Salgado",
        "link": null,
        "place": 30,
        "time": 45
      },
      {
        "userId": 453034,
        "user": "Epiphane (AoC++)",
        "link": "https://github.com/Epiphane",
        "place": 31,
        "time": 45
      },
      {
        "userId": 279226,
        "user": "kevinmchung (AoC++)",
        "link": "https://github.com/kevinmchung",
        "place": 32,
        "time": 45
      },
      {
        "userId": 433239,
        "user": "Emil Hvitfeldt",
        "link": "https://github.com/EmilHvitfeldt",
        "place": 33,
        "time": 47
      },
      {
        "userId": 277745,
        "user": "dan-simon",
        "link": null,
        "place": 34,
        "time": 47
      },
      {
        "userId": 406017,
        "user": "Erik Szalay",
        "link": null,
        "place": 35,
        "time": 48
      },
      {
        "userId": 733583,
        "user": "Bradley Steel",
        "link": null,
        "place": 36,
        "time": 48
      },
      {
        "userId": 31389,
        "user": "aleksejspopovs",
        "link": null,
        "place": 37,
        "time": 48
      },
      {
        "userId": 540750,
        "user": "Sumner Evans (AoC++)",
        "link": "https://github.com/sumnerevans",
        "place": 38,
        "time": 49
      },
      {
        "userId": 112827,
        "user": "Toni Fadjukoff (AoC++)",
        "link": "/2021/support",
        "place": 39,
        "time": 49
      },
      {
        "userId": 1126589,
        "user": "Kathryn Tang (AoC++) (Sponsor)",
        "link": "/2021/support",
        "place": 40,
        "time": 49
      },
      {
        "userId": 1029934,
        "user": "yutu58 (AoC++)",
        "link": "https://github.com/yutu58",
        "place": 41,
        "time": 49
      },
      {
        "userId": 389017,
        "user": "goffrie",
        "link": null,
        "place": 42,
        "time": 49
      },
      {
        "userId": 111831,
        "user": "jebouin (AoC++)",
        "link": "https://github.com/jebouin",
        "place": 43,
        "time": 50
      },
      {
        "userId": 47898,
        "user": "anominos",
        "link": "https://github.com/anominos",
        "place": 44,
        "time": 50
      },
      {
        "userId": 881636,
        "user": "mayoff (AoC++)",
        "link": "https://github.com/mayoff",
        "place": 45,
        "time": 50
      },
      {
        "userId": 644347,
        "user": "Miriam Vellacott",
        "link": "https://github.com/Artemis21",
        "place": 46,
        "time": 51
      },
      {
        "userId": 1567705,
        "user": "Kingsley Zhong",
        "link": null,
        "place": 47,
        "time": 51
      },
      {
        "userId": 1495169,
        "user": "skeole",
        "link": null,
        "place": 48,
        "time": 52
      },
      {
        "userId": 242646,
        "user": "Matt Gruskin (AoC++)",
        "link": "/2021/support",
        "place": 49,
        "time": 52
      },
      {
        "userId": 993072,
        "user": "KevinL10",
        "link": "https://github.com/KevinL10",
        "place": 50,
        "time": 53
      },
      {
        "userId": 152693,
        "user": "Lars Haulin (AoC++)",
        "link": "/2021/support",
        "place": 51,
        "time": 53
      },
      {
        "userId": 282206,
        "user": "ecnerwala",
        "link": "https://github.com/ecnerwala",
        "place": 52,
        "time": 53
      },
      {
        "userId": 1382631,
        "user": "RundownRhino",
        "link": "https://github.com/RundownRhino",
        "place": 53,
        "time": 54
      },
      {
        "userId": 475191,
        "user": "bluepichu",
        "link": "https://github.com/bluepichu",
        "place": 54,
        "time": 54
      },
      {
        "userId": 133207,
        "user": "Robert Xiao",
        "link": "https://github.com/nneonneo",
        "place": 55,
        "time": 54
      },
      {
        "userId": 312956,
        "user": "Søren Fuglede Jørgensen (AoC++)",
        "link": "https://github.com/fuglede",
        "place": 56,
        "time": 55
      },
      {
        "userId": 379846,
        "user": "Nathan Fenner (AoC++)",
        "link": "https://github.com/Nathan-Fenner",
        "place": 57,
        "time": 55
      },
      {
        "userId": 3635,
        "user": "Lukas Froehlich",
        "link": null,
        "place": 58,
        "time": 55
      },
      {
        "userId": 1111582,
        "user": "Chris Bernt",
        "link": null,
        "place": 59,
        "time": 55
      },
      {
        "userId": 1154419,
        "user": "Corncycle",
        "link": null,
        "place": 60,
        "time": 55
      },
      {
        "userId": 286524,
        "user": "Thomas Feld",
        "link": null,
        "place": 61,
        "time": 55
      },
      {
        "userId": 430879,
        "user": "nlc",
        "link": null,
        "place": 62,
        "time": 56
      },
      {
        "userId": 716562,
        "user": "kjsatz",
        "link": "https://github.com/kjsatz",
        "place": 63,
        "time": 56
      },
      {
        "userId": 513100,
        "user": "twattanawaroon",
        "link": null,
        "place": 64,
        "time": 57
      },
      {
        "userId": 664169,
        "user": "Carson Graham",
        "link": "https://github.com/Mee42",
        "place": 65,
        "time": 57
      },
      {
        "userId": 843547,
        "user": "Taras Gritsenko",
        "link": "https://github.com/qubard",
        "place": 66,
        "time": 57
      },
      {
        "userId": 11133,
        "user": "msullivan (AoC++)",
        "link": "https://github.com/msullivan",
        "place": 67,
        "time": 57
      },
      {
        "userId": 189889,
        "user": "Leon Loopik (AoC++)",
        "link": "https://github.com/Lewn",
        "place": 68,
        "time": 57
      },
      {
        "userId": 75249,
        "user": "petertseng (AoC++)",
        "link": "https://github.com/petertseng",
        "place": 69,
        "time": 58
      },
      {
        "userId": 995524,
        "user": "Oliver Ni (AoC++)",
        "link": "https://github.com/oliver-ni",
        "place": 70,
        "time": 59
      },
      {
        "userId": 13379,
        "user": "Aaron-Pierce",
        "link": null,
        "place": 71,
        "time": 60
      },
      {
        "userId": 184890,
        "user": "Jacob Magnuson (AoC++)",
        "link": "/2021/support",
        "place": 72,
        "time": 60
      },
      {
        "userId": 386687,
        "user": "BjornMagn",
        "link": null,
        "place": 73,
        "time": 60
      },
      {
        "userId": 767098,
        "user": "Ryan Hitchman",
        "link": "https://github.com/rmmh",
        "place": 74,
        "time": 60
      },
      {
        "userId": 988295,
        "user": "Sunny Guan",
        "link": "https://github.com/sunnyguan",
        "place": 75,
        "time": 60
      },
      {
        "userId": 603280,
        "user": "Reed Hamilton (AoC++)",
        "link": "/2021/support",
        "place": 76,
        "time": 60
      },
      {
        "userId": 491457,
        "user": "Apollo",
        "link": null,
        "place": 77,
        "time": 60
      },
      {
        "userId": 55305,
        "user": "Unihedron",
        "link": "https://github.com/Unihedro",
        "place": 78,
        "time": 61
      },
      {
        "userId": 427936,
        "user": "Waffle",
        "link": null,
        "place": 79,
        "time": 61
      },
      {
        "userId": 66333,
        "user": "Zack Chroman",
        "link": null,
        "place": 80,
        "time": 61
      },
      {
        "userId": 766119,
        "user": "dipernalz (AoC++)",
        "link": "https://github.com/dipernalz",
        "place": 81,
        "time": 62
      },
      {
        "userId": 488230,
        "user": "(anonymous user #488230)",
        "link": null,
        "place": 82,
        "time": 62
      },
      {
        "userId": 418553,
        "user": "ruuddotorg",
        "link": null,
        "place": 83,
        "time": 62
      },
      {
        "userId": 242096,
        "user": "artcz (AoC++)",
        "link": "https://github.com/artcz",
        "place": 84,
        "time": 62
      },
      {
        "userId": 429168,
        "user": "DayDun",
        "link": "https://github.com/DayDun",
        "place": 85,
        "time": 62
      },
      {
        "userId": 840765,
        "user": "Larry",
        "link": null,
        "place": 86,
        "time": 62
      },
      {
        "userId": 637730,
        "user": "vukonen",
        "link": "https://github.com/vukonen",
        "place": 87,
        "time": 63
      },
      {
        "userId": 1570001,
        "user": "abertell",
        "link": "https://github.com/abertell",
        "place": 88,
        "time": 63
      },
      {
        "userId": 389935,
        "user": "gabekanegae",
        "link": "https://github.com/gabekanegae",
        "place": 89,
        "time": 63
      },
      {
        "userId": 673742,
        "user": "Bahnschrift",
        "link": "https://github.com/Bahnschrift",
        "place": 90,
        "time": 63
      },
      {
        "userId": 385252,
        "user": "Ovidiu Firescu",
        "link": "https://github.com/FirescuOvidiu",
        "place": 91,
        "time": 63
      },
      {
        "userId": 243316,
        "user": "mingmingrr",
        "link": null,
        "place": 92,
        "time": 63
      },
      {
        "userId": 159341,
        "user": "DylanDmitri",
        "link": null,
        "place": 93,
        "time": 64
      },
      {
        "userId": 614948,
        "user": "Alexander Haupt",
        "link": "https://github.com/alexanderhaupt",
        "place": 94,
        "time": 64
      },
      {
        "userId": 189723,
        "user": "Joel Jonsson (AoC++)",
        "link": "https://github.com/joeljons",
        "place": 95,
        "time": 64
      },
      {
        "userId": 1121078,
        "user": "William Tsin",
        "link": "https://github.com/bucketpotato01",
        "place": 96,
        "time": 64
      },
      {
        "userId": 1541781,
        "user": "Daniel Yang",
        "link": null,
        "place": 97,
        "time": 64
      },
      {
        "userId": 107707,
        "user": "Måns Magnusson",
        "link": "https://github.com/exoji2e",
        "place": 98,
        "time": 65
      },
      {
        "userId": 1545252,
        "user": "(anonymous user #1545252)",
        "link": null,
        "place": 99,
        "time": 65
      },
      {
        "userId": 1533299,
        "user": "Joe L.",
        "link": "https://github.com/jo3-l",
        "place": 100,
        "time": 65
      }
    ],
    "2": [
      {
        "userId": 52063,
        "user": "Tanner Hoke",
        "link": null,
        "place": 1,
        "time": 67
      },
      {
        "userId": 379289,
        "user": "Erik Amirell Eklöf",
        "link": "https://github.com/Eae02",
        "place": 2,
        "time": 72
      },
      {
        "userId": 996955,
        "user": "David Robinson",
        "link": "https://twitter.com/drob",
        "place": 3,
        "time": 73
      },
      {
        "userId": 417403,
        "user": "bjebert",
        "link": "https://github.com/bjebert",
        "place": 4,
        "time": 74
      },
      {
        "userId": 201408,
        "user": "Tim Vermeulen (AoC++)",
        "link": "https://github.com/timvermeulen",
        "place": 5,
        "time": 78
      },
      {
        "userId": 277745,
        "user": "dan-simon",
        "link": null,
        "place": 6,
        "time": 86
      },
      {
        "userId": 995524,
        "user": "Oliver Ni (AoC++)",
        "link": "https://github.com/oliver-ni",
        "place": 7,
        "time": 89
      },
      {
        "userId": 1495169,
        "user": "skeole",
        "link": null,
        "place": 8,
        "time": 90
      },
      {
        "userId": 415650,
        "user": "tckmn",
        "link": "https://github.com/tckmn",
        "place": 9,
        "time": 92
      },
      {
        "userId": 677741,
        "user": "(anonymous user #677741) (AoC++)",
        "link": "/2021/support",
        "place": 10,
        "time": 93
      },
      {
        "userId": 389017,
        "user": "goffrie",
        "link": null,
        "place": 11,
        "time": 98
      },
      {
        "userId": 389935,
        "user": "gabekanegae",
        "link": "https://github.com/gabekanegae",
        "place": 12,
        "time": 98
      },
      {
        "userId": 430879,
        "user": "nlc",
        "link": null,
        "place": 13,
        "time": 101
      },
      {
        "userId": 223257,
        "user": "mcpower",
        "link": "https://github.com/mcpower",
        "place": 14,
        "time": 102
      },
      {
        "userId": 102628,
        "user": "kejadlen (AoC++)",
        "link": "https://github.com/kejadlen",
        "place": 15,
        "time": 103
      },
      {
        "userId": 484659,
        "user": "Craig Gidney (AoC++)",
        "link": "https://github.com/Strilanc",
        "place": 16,
        "time": 103
      },
      {
        "userId": 75249,
        "user": "petertseng (AoC++)",
        "link": "https://github.com/petertseng",
        "place": 17,
        "time": 104
      },
      {
        "userId": 1124805,
        "user": "T6",
        "link": "https://github.com/tjjfvi",
        "place": 18,
        "time": 105
      },
      {
        "userId": 406017,
        "user": "Erik Szalay",
        "link": null,
        "place": 19,
        "time": 105
      },
      {
        "userId": 282206,
        "user": "ecnerwala",
        "link": "https://github.com/ecnerwala",
        "place": 20,
        "time": 105
      },
      {
        "userId": 645988,
        "user": "qpwoeirut",
        "link": "https://github.com/qpwoeirut",
        "place": 21,
        "time": 106
      },
      {
        "userId": 351052,
        "user": "Md Abedin",
        "link": "https://github.com/MdAbedin",
        "place": 22,
        "time": 106
      },
      {
        "userId": 475191,
        "user": "bluepichu",
        "link": "https://github.com/bluepichu",
        "place": 23,
        "time": 106
      },
      {
        "userId": 427936,
        "user": "Waffle",
        "link": null,
        "place": 24,
        "time": 107
      },
      {
        "userId": 264367,
        "user": "awychong",
        "link": null,
        "place": 25,
        "time": 108
      },
      {
        "userId": 1510407,
        "user": "(anonymous user #1510407) (AoC++)",
        "link": "/2021/support",
        "place": 26,
        "time": 108
      },
      {
        "userId": 32289,
        "user": "betaveros (AoC++)",
        "link": "https://github.com/betaveros",
        "place": 27,
        "time": 109
      },
      {
        "userId": 189723,
        "user": "Joel Jonsson (AoC++)",
        "link": "https://github.com/joeljons",
        "place": 28,
        "time": 110
      },
      {
        "userId": 993072,
        "user": "KevinL10",
        "link": "https://github.com/KevinL10",
        "place": 29,
        "time": 112
      },
      {
        "userId": 733583,
        "user": "Bradley Steel",
        "link": null,
        "place": 30,
        "time": 113
      },
      {
        "userId": 705153,
        "user": "5space",
        "link": "https://github.com/5space",
        "place": 31,
        "time": 114
      },
      {
        "userId": 514396,
        "user": "connorjayr (AoC++)",
        "link": "https://github.com/connorjayr",
        "place": 32,
        "time": 116
      },
      {
        "userId": 13379,
        "user": "Aaron-Pierce",
        "link": null,
        "place": 33,
        "time": 116
      },
      {
        "userId": 152693,
        "user": "Lars Haulin (AoC++)",
        "link": "/2021/support",
        "place": 34,
        "time": 116
      },
      {
        "userId": 31389,
        "user": "aleksejspopovs",
        "link": null,
        "place": 35,
        "time": 119
      },
      {
        "userId": 1570001,
        "user": "abertell",
        "link": "https://github.com/abertell",
        "place": 36,
        "time": 119
      },
      {
        "userId": 808370,
        "user": "VasilyDK",
        "link": null,
        "place": 37,
        "time": 121
      },
      {
        "userId": 645166,
        "user": "shinyclovers",
        "link": null,
        "place": 38,
        "time": 122
      },
      {
        "userId": 632862,
        "user": "GregorKikelj",
        "link": "https://github.com/GregorKikelj",
        "place": 39,
        "time": 124
      },
      {
        "userId": 312956,
        "user": "Søren Fuglede Jørgensen (AoC++)",
        "link": "https://github.com/fuglede",
        "place": 40,
        "time": 124
      },
      {
        "userId": 11133,
        "user": "msullivan (AoC++)",
        "link": "https://github.com/msullivan",
        "place": 41,
        "time": 125
      },
      {
        "userId": 962724,
        "user": "boboquack",
        "link": null,
        "place": 42,
        "time": 126
      },
      {
        "userId": 379846,
        "user": "Nathan Fenner (AoC++)",
        "link": "https://github.com/Nathan-Fenner",
        "place": 43,
        "time": 126
      },
      {
        "userId": 1154419,
        "user": "Corncycle",
        "link": null,
        "place": 44,
        "time": 128
      },
      {
        "userId": 633174,
        "user": "anna (AoC++)",
        "link": "https://github.com/anna328p",
        "place": 45,
        "time": 129
      },
      {
        "userId": 987142,
        "user": "Mathgeek007",
        "link": null,
        "place": 46,
        "time": 129
      },
      {
        "userId": 1568745,
        "user": "Daniel Strizhevsky",
        "link": "https://github.com/danielstrizhevsky",
        "place": 47,
        "time": 129
      },
      {
        "userId": 429168,
        "user": "DayDun",
        "link": "https://github.com/DayDun",
        "place": 48,
        "time": 129
      },
      {
        "userId": 1126589,
        "user": "Kathryn Tang (AoC++) (Sponsor)",
        "link": "/2021/support",
        "place": 49,
        "time": 130
      },
      {
        "userId": 688160,
        "user": "leijurv (AoC++)",
        "link": "https://github.com/leijurv",
        "place": 50,
        "time": 131
      },
      {
        "userId": 840765,
        "user": "Larry",
        "link": null,
        "place": 51,
        "time": 131
      },
      {
        "userId": 513100,
        "user": "twattanawaroon",
        "link": null,
        "place": 52,
        "time": 131
      },
      {
        "userId": 226479,
        "user": "Ryan Norris",
        "link": "https://github.com/rynorris",
        "place": 53,
        "time": 133
      },
      {
        "userId": 994323,
        "user": "Carl Schildkraut",
        "link": null,
        "place": 54,
        "time": 134
      },
      {
        "userId": 67806,
        "user": "jonathanpaulson (AoC++)",
        "link": "https://github.com/jonathanpaulson",
        "place": 55,
        "time": 134
      },
      {
        "userId": 1215342,
        "user": "(anonymous user #1215342)",
        "link": null,
        "place": 56,
        "time": 134
      },
      {
        "userId": 418553,
        "user": "ruuddotorg",
        "link": null,
        "place": 57,
        "time": 134
      },
      {
        "userId": 31743,
        "user": "Antonio Molina",
        "link": null,
        "place": 58,
        "time": 136
      },
      {
        "userId": 60233,
        "user": "(anonymous user #60233) (AoC++)",
        "link": "/2021/support",
        "place": 59,
        "time": 138
      },
      {
        "userId": 881636,
        "user": "mayoff (AoC++)",
        "link": "https://github.com/mayoff",
        "place": 60,
        "time": 138
      },
      {
        "userId": 217709,
        "user": "(anonymous user #217709) (AoC++)",
        "link": "/2021/support",
        "place": 61,
        "time": 140
      },
      {
        "userId": 627919,
        "user": "Graham White",
        "link": null,
        "place": 62,
        "time": 140
      },
      {
        "userId": 169506,
        "user": "ghlmtz",
        "link": null,
        "place": 63,
        "time": 141
      },
      {
        "userId": 279226,
        "user": "kevinmchung (AoC++)",
        "link": "https://github.com/kevinmchung",
        "place": 64,
        "time": 141
      },
      {
        "userId": 1121078,
        "user": "William Tsin",
        "link": "https://github.com/bucketpotato01",
        "place": 65,
        "time": 141
      },
      {
        "userId": 540750,
        "user": "Sumner Evans (AoC++)",
        "link": "https://github.com/sumnerevans",
        "place": 66,
        "time": 142
      },
      {
        "userId": 673742,
        "user": "Bahnschrift",
        "link": "https://github.com/Bahnschrift",
        "place": 67,
        "time": 143
      },
      {
        "userId": 453034,
        "user": "Epiphane (AoC++)",
        "link": "https://github.com/Epiphane",
        "place": 68,
        "time": 145
      },
      {
        "userId": 55305,
        "user": "Unihedron",
        "link": "https://github.com/Unihedro",
        "place": 69,
        "time": 146
      },
      {
        "userId": 199929,
        "user": "(anonymous user #199929)",
        "link": null,
        "place": 70,
        "time": 146
      },
      {
        "userId": 29354,
        "user": "Samuel Eisenhandler (AoC++)",
        "link": "https://github.com/sgeisenh",
        "place": 71,
        "time": 147
      },
      {
        "userId": 1533299,
        "user": "Joe L.",
        "link": "https://github.com/jo3-l",
        "place": 72,
        "time": 147
      },
      {
        "userId": 1502840,
        "user": "Markus Himmel (AoC++)",
        "link": "https://github.com/TwoFX",
        "place": 73,
        "time": 147
      },
      {
        "userId": 1069150,
        "user": "Timothy Mou",
        "link": null,
        "place": 74,
        "time": 148
      },
      {
        "userId": 169617,
        "user": "asishm",
        "link": "https://github.com/asishm",
        "place": 75,
        "time": 148
      },
      {
        "userId": 196727,
        "user": "hyperneutrino (AoC++)",
        "link": "https://github.com/hyperneutrino",
        "place": 76,
        "time": 150
      },
      {
        "userId": 682093,
        "user": "Daniel Kempner",
        "link": "https://github.com/dkempner",
        "place": 77,
        "time": 151
      },
      {
        "userId": 269371,
        "user": "skaldskaparmal",
        "link": null,
        "place": 78,
        "time": 152
      },
      {
        "userId": 3552,
        "user": "Kristian Bjerre Schmidt (AoC++)",
        "link": "/2021/support",
        "place": 79,
        "time": 152
      },
      {
        "userId": 798625,
        "user": "LyricLy",
        "link": "https://github.com/LyricLy",
        "place": 80,
        "time": 154
      },
      {
        "userId": 1008213,
        "user": "rhendric",
        "link": null,
        "place": 81,
        "time": 154
      },
      {
        "userId": 992497,
        "user": "xupej04m3",
        "link": null,
        "place": 82,
        "time": 154
      },
      {
        "userId": 312289,
        "user": "Evan Kwan",
        "link": null,
        "place": 83,
        "time": 154
      },
      {
        "userId": 953558,
        "user": "Maxwell Zen",
        "link": "https://github.com/MaxwellZen",
        "place": 84,
        "time": 155
      },
      {
        "userId": 107707,
        "user": "Måns Magnusson",
        "link": "https://github.com/exoji2e",
        "place": 85,
        "time": 156
      },
      {
        "userId": 63186,
        "user": "abnew123",
        "link": "https://github.com/abnew123",
        "place": 86,
        "time": 156
      },
      {
        "userId": 988295,
        "user": "Sunny Guan",
        "link": "https://github.com/sunnyguan",
        "place": 87,
        "time": 156
      },
      {
        "userId": 1058622,
        "user": "nathanlo99",
        "link": "https://github.com/nathanlo99",
        "place": 88,
        "time": 157
      },
      {
        "userId": 243316,
        "user": "mingmingrr",
        "link": null,
        "place": 89,
        "time": 158
      },
      {
        "userId": 65338,
        "user": "Oleg Godovykh (AoC++)",
        "link": "https://github.com/0legg",
        "place": 90,
        "time": 159
      },
      {
        "userId": 1067303,
        "user": "alecbrick",
        "link": "https://github.com/alecbrick",
        "place": 91,
        "time": 159
      },
      {
        "userId": 644309,
        "user": "Defelo (AoC++)",
        "link": "https://github.com/Defelo",
        "place": 92,
        "time": 159
      },
      {
        "userId": 994103,
        "user": "btnlq",
        "link": null,
        "place": 93,
        "time": 160
      },
      {
        "userId": 26414,
        "user": "mserrano",
        "link": null,
        "place": 94,
        "time": 160
      },
      {
        "userId": 518776,
        "user": "zgotsch",
        "link": null,
        "place": 95,
        "time": 160
      },
      {
        "userId": 423077,
        "user": "John Hornibrook",
        "link": null,
        "place": 96,
        "time": 161
      },
      {
        "userId": 122818,
        "user": "Michael Goldwasser",
        "link": null,
        "place": 97,
        "time": 161
      },
      {
        "userId": 1077011,
        "user": "Aadit Ambadkar",
        "link": null,
        "place": 98,
        "time": 162
      },
      {
        "userId": 357720,
        "user": "0e4ef622",
        "link": "https://github.com/0e4ef622",
        "place": 99,
        "time": 163
      },
      {
        "userId": 381872,
        "user": "HeyItsBATMAN (AoC++)",
        "link": "https://github.com/HeyItsBATMAN",
        "place": 100,
        "time": 164
      }
    ]
  }
}